erpbrasil.bank.inter-1.1.0-py3.11-nspkg.pth
erpbrasil/bank/__init__.py
erpbrasil/bank/inter/__init__.py
erpbrasil/bank/inter/__main__.py
erpbrasil/bank/inter/api.py
erpbrasil/bank/inter/boleto.py
erpbrasil/bank/inter/cli.py
erpbrasil.bank.inter-1.1.0.dist-info/AUTHORS.rst
erpbrasil.bank.inter-1.1.0.dist-info/LICENSE
erpbrasil.bank.inter-1.1.0.dist-info/METADATA
erpbrasil.bank.inter-1.1.0.dist-info/WHEEL
erpbrasil.bank.inter-1.1.0.dist-info/entry_points.txt
erpbrasil.bank.inter-1.1.0.dist-info/namespace_packages.txt
erpbrasil.bank.inter-1.1.0.dist-info/top_level.txt
erpbrasil.bank.inter-1.1.0.dist-info/RECORD
